.bumpversion.cfg
.cookiecutterrc
.coveragerc
.editorconfig
.travis.yml
AUTHORS.rst
CHANGELOG.rst
CONTRIBUTING.rst
LICENSE
MANIFEST.in
README.rst
setup.cfg
setup.py
tox.ini
ci/bootstrap.py
docs/authors.rst
docs/changelog.rst
docs/conf.py
docs/contributing.rst
docs/index.rst
docs/installation.rst
docs/readme.rst
docs/requirements.txt
docs/spelling_wordlist.txt
docs/usage.rst
docs/reference/decorated_options.rst
docs/reference/index.rst
src/decorated_options/__init__.py
src/decorated_options/__init__.py.orig
src/decorated_options/__init__.py~
src/decorated_options/options.py
src/decorated_options/options.py.orig
src/decorated_options/options.py~
src/decorated_options.egg-info/PKG-INFO
src/decorated_options.egg-info/SOURCES.txt
src/decorated_options.egg-info/dependency_links.txt
src/decorated_options.egg-info/not-zip-safe
src/decorated_options.egg-info/top_level.txt
tests/test_decorated_options.py
tests/test_decorated_options.py.orig
tests/test_decorated_options.py~