Metadata-Version: 1.1
Name: decorated-options
Version: 0.1.0
Summary: Function decorator to make argument passing saner.
Home-page: https://github.com/musically-ut/decorated_options
Author: Utkarsh Upadhyay
Author-email: mail@musicallyut.in
License: BSD
Keywords: decorators,data-science,configuration,arguments
Platform: UNKNOWN
Classifier: Development Status :: 3 - Alpha
Classifier: Intended Audience :: Developers
Classifier: Intended Audience :: Science/Research
Classifier: License :: OSI Approved :: BSD License
Classifier: Operating System :: Unix
Classifier: Operating System :: POSIX
Classifier: Operating System :: Microsoft :: Windows
Classifier: Programming Language :: Python
Classifier: Programming Language :: Python :: 3.3
Classifier: Programming Language :: Python :: 3.4
Classifier: Programming Language :: Python :: 3.5
Classifier: Topic :: Utilities
